dmario24_lotto/__init__.py
dmario24_lotto/draw.py
dmario24_lotto-0.2.0.dist-info/METADATA
dmario24_lotto-0.2.0.dist-info/WHEEL
dmario24_lotto-0.2.0.dist-info/top_level.txt
dmario24_lotto-0.2.0.dist-info/RECORD
