Metadata-Version: 2.1
Name: dmario24_lotto
Version: 0.2.0
Summary: Default template for PDM package
Author-email: dMario24 <data.mario24@gmail.com>
License: MIT
Requires-Python: >=3.9
